fastapi_rfc7807/__init__.py
fastapi_rfc7807/middleware.py
fastapi_rfc7807/py.typed
fastapi_rfc7807/schema.py
fastapi_rfc7807-0.5.0.dist-info/LICENSE
fastapi_rfc7807-0.5.0.dist-info/METADATA
fastapi_rfc7807-0.5.0.dist-info/WHEEL
fastapi_rfc7807-0.5.0.dist-info/top_level.txt
fastapi_rfc7807-0.5.0.dist-info/RECORD
