Metadata-Version: 2.1
Name: fastapi-rfc7807
Version: 0.5.0
Summary: FastAPI middleware for RFC-7807 compliant error responses
Home-page: https://github.com/vapor-ware/fastapi-rfc7807
Author: Erick Daniszewski
Author-email: erick@vapor.io
License: GNU General Public License v3.0
Keywords: fastapi,errors,middleware,rfc7807
Platform: UNKNOWN
Classifier: Intended Audience :: Developers
Classifier: Programming Language :: Python :: 3
Classifier: Programming Language :: Python :: 3.6
Classifier: Programming Language :: Python :: 3.7
Classifier: Programming Language :: Python :: 3.8
Classifier: Programming Language :: Python :: 3.9
Classifier: License :: OSI Approved :: GNU General Public License v3 (GPLv3)
Classifier: Operating System :: OS Independent
Requires-Python: >=3.6
License-File: LICENSE
Requires-Dist: fastapi
Requires-Dist: starlette
Requires-Dist: pydantic
